kemux/__init__.py
kemux/manager.py
kemux/data/__init__.py
kemux/data/stream.py
kemux/data/processor/__init__.py
kemux/data/processor/base.py
kemux/data/processor/input.py
kemux/data/processor/output.py
kemux/data/schema/__init__.py
kemux/data/schema/base.py
kemux/data/schema/input.py
kemux/data/schema/output.py
kemux/logic/__init__.py
kemux/logic/imports.py
kemux-1.0.2b1.dist-info/LICENSE
kemux-1.0.2b1.dist-info/METADATA
kemux-1.0.2b1.dist-info/WHEEL
kemux-1.0.2b1.dist-info/top_level.txt
kemux-1.0.2b1.dist-info/RECORD
