Metadata-Version: 2.1
Name: kemux
Version: 1.0.2b1
Summary: Python interface for splitting and/or merging Kafka topics
Home-page: https://kemux.readthedocs.io/en/latest
Author: Kamil Rybacki
Author-email: kamilandrzejrybacki@gmail.com
License-File: LICENSE
Requires-Dist: faust-streaming ==0.10.14
